{"O1hR524LI/s37wQiSIVrrw==":"1logo-910x340.png","gHZDPFQGtrV/ourpxfXhgw==":"img-5280-674x681.jpg","DbIS5lbMPeZoU7qf6oBMZA==":"img-5427-750x731.jpg","Mg3jBMZCXPkRyQItqCJqJw==":"img-5428-750x731.jpg","I3N1UfTQJ7Mq+Bp07AbaPA==":"img-5429-750x731.jpg","7w/MTW6f1TTY3ih4okfO6A==":"1logo-1597x597.png","05GMASoSecijzExgJvMYxA==":"feet-737x665.png","64OErVlf/C93V+Kv/yK2Mg==":"img-5455-750x753.jpg","k718zjgJT4wesjuI+phLKA==":"img-5331-750x740.jpg","DW4ls7IcEEyGZeby12zwWg==":"nailspage%20-%20copy-640x483.jpg","S8MUvvza8Wlu82oEdONphw==":"nailspage%20-%20copy-640x483.jpg","+RIt5tgBvgzZ9UZkAvvZug==":"nailspage2%20-%20copy-606x640.jpg","k0XcKYLoWKqY+Zi5YxRj1w==":"img-5464-640x638.jpg","i6nve8GhhAprn3sPWP7LVg==":"1logo-1380x516.png"}